SDG_LLM/__init__.py
SDG_LLM/document_loaders.py
SDG_LLM/prompt_loaders.py
SDG_LLM/text_extarcters.py
SDG_LLM/text_spliters.py
SDG_LLM/utlis.py
SDG_LLM-0.0.5.dist-info/METADATA
SDG_LLM-0.0.5.dist-info/WHEEL
SDG_LLM-0.0.5.dist-info/top_level.txt
SDG_LLM-0.0.5.dist-info/RECORD
