Metadata-Version: 2.1
Name: SDG_LLM
Version: 0.0.5
Summary: Synthetic data generator for LLM evaluation
Author: Darshan Kumar
Author-email: Darshan Kumar <Darshankumarr03@gmail.com>
License: MIT
Project-URL: Source, https://github.com/Darshanroy/synthetic-data-generator.git
Project-URL: Tracker, https://github.com/Darshanroy/synthetic-data-generator/issues
Requires-Python: >=3.7
